[
  {
    "metadata": {
      "id": "arc_001",
      "terminal_inicio": "LO BLANCO",
      "terminal_fin": "RECOLETA",
      "servicio": "RE-LB-SR",
      "sentido": "IDA",
      "calles": "Av Lo Blanco|Av San Francisco|Venancia Leiva|Av San Francisco|Cerro Negro|La Granja|San Francisco|Av Lo Ovalle|León Tolstoi|Esmeralda|Vargas Buston|San Francisco|Av Departamental|Frankfort|Av Berlín|Gran Av José Miguel Carrera|San Diego|Tarapacá|Zenteno|Morandé|San Pablo|Bandera|Av La Paz|Profesor Alberto Zañartu|La Unión|Av Recoleta",
      "notas": "",
      "activo": "sí"
    },
    "geometria": null
  },
  {
    "metadata": {
      "id": "arc_002",
      "terminal_inicio": "RECOLETA",
      "terminal_fin": "LO BLANCO",
      "servicio": "RE-LB-SR",
      "sentido": "VUELTA",
      "calles": "Av Recoleta|La Unión|Profesor Alberto Zañartu|Av La Paz|Bandera|San Pablo|Morandé|Zenteno|Tarapacá|San Diego|Gran Av José Miguel Carrera|Av Berlín|Frankfort|Av Departamental|San Francisco|Vargas Buston|Esmeralda|León Tolstoi|Av Lo Ovalle|San Francisco|La Granja|Cerro Negro|Av San Francisco|Venancia Leiva|Av San Francisco|Av Lo Blanco",
      "notas": "Reverso de arc_001 - validar calles unidireccionales",
      "activo": "sí"
    },
    "geometria": null
  },
  {
    "metadata": {
      "id": "arc_003",
      "terminal_inicio": "RECOLETA",
      "terminal_fin": "LAS CAÑAS",
      "servicio": "RE-LB-SR",
      "sentido": "IDA",
      "calles": "Av Salvador Allende,Av Recoleta,Av Dorsal,Bajos de Jiménez",
      "notas": "",
      "activo": "sí"
    },
    "geometria": {
      "type": "LineString",
      "coordinates": [
        [
          -70.637904,
          -33.378829
        ],
        [
          -70.638023,
          -33.378683
        ],
        [
          -70.638696,
          -33.378545
        ],
        [
          -70.639087,
          -33.379496
        ],
        [
          -70.640437,
          -33.382702
        ],
        [
          -70.641182,
          -33.384862
        ],
        [
          -70.642266,
          -33.387595
        ],
        [
          -70.642471,
          -33.391432
        ],
        [
          -70.642675,
          -33.394616
        ],
        [
          -70.642727,
          -33.396535
        ],
        [
          -70.647063,
          -33.395921
        ],
        [
          -70.650399,
          -33.395623
        ],
        [
          -70.653339,
          -33.395092
        ],
        [
          -70.655392,
          -33.395301
        ],
        [
          -70.661108,
          -33.396205
        ],
        [
          -70.664983,
          -33.396894
        ],
        [
          -70.668296,
          -33.39734
        ],
        [
          -70.669813,
          -33.397789
        ],
        [
          -70.670719,
          -33.398335
        ],
        [
          -70.671473,
          -33.398673
        ],
        [
          -70.672828,
          -33.398986
        ],
        [
          -70.679599,
          -33.401383
        ],
        [
          -70.681318,
          -33.401971
        ],
        [
          -70.680679,
          -33.403085
        ],
        [
          -70.679921,
          -33.404104
        ],
        [
          -70.678261,
          -33.405952
        ]
      ]
    }
  },
  {
    "metadata": {
      "id": "arc_004",
      "terminal_inicio": "LAS CAÑAS",
      "terminal_fin": "RECOLETA",
      "servicio": "RE-LB-SR",
      "sentido": "VUELTA",
      "calles": "Bajos de Jiménez,Av Dorsal,Av Recoleta,Av Salvador Allende",
      "notas": "Termina con Salvador Allende para entrar al terminal de Recoleta",
      "activo": "sí"
    },
    "geometria": null
  },
  {
    "metadata": {
      "id": "arc_005",
      "terminal_inicio": "PEDRO LIRA",
      "terminal_fin": "RECOLETA",
      "servicio": "RE-LB-SR",
      "sentido": "VUELTA",
      "calles": "PEDRO LIRA, GIL DE CASTRO, AV. CENTRAL CARDENAL RAÚL SILVA HENRÍQUEZ, AV. AMERICO VESPUCIO, ENLACE AMÉRICO VESPUCIO ORIENTE, AV. JOSÉ JOAQUÍN PRIETO VIAL, AV. VIEL, AV. MANUEL RODRIGUEZ, GENERAL MACKENNA, ISMAEL VALDES VERGARA, AV. RECOLETA, AV. PRESIDENTE SALVADOR ALLENDE, PATIO RECOLETA",
      "notas": "",
      "activo": "sí"
    },
    "geometria": null
  },
  {
    "metadata": {
      "id": "arc_006",
      "terminal_inicio": "RECOLETA",
      "terminal_fin": "PEDRO LIRA",
      "servicio": "RE-LB-SR",
      "sentido": "IDA",
      "calles": "PATIO RECOLETA, AV. PRESIDENTE SALVADOR ALLENDE, AV. RECOLETA, AV. CARDENAL JOSÉ MARÍA CARO, AV. PRESIDENTE BALMACEDA, AV. MANUEL RODRIGUEZ, AV. VIEL, AV. JOSÉ JOAQUÍN PRIETO VIAL, ENLACE AMÉRICO VESPUCIO PONIENTE, AV. AMERICO VESPUCIO, AV. CENTRAL CARDENAL RAÚL SILVA HENRÍQUEZ, GIL DE CASTRO, PEDRO LIRA",
      "notas": "",
      "activo": "sí"
    },
    "geometria": {
      "type": "LineString",
      "coordinates": [
        [
          -70.637857,
          -33.378858
        ],
        [
          -70.637969,
          -33.378721
        ],
        [
          -70.638691,
          -33.378552
        ],
        [
          -70.638978,
          -33.379177
        ],
        [
          -70.640227,
          -33.382409
        ],
        [
          -70.64069,
          -33.383026
        ],
        [
          -70.640775,
          -33.383401
        ],
        [
          -70.640848,
          -33.383925
        ],
        [
          -70.641048,
          -33.384528
        ],
        [
          -70.641889,
          -33.386587
        ],
        [
          -70.642252,
          -33.387458
        ],
        [
          -70.642311,
          -33.388385
        ],
        [
          -70.642344,
          -33.38918
        ],
        [
          -70.642556,
          -33.392583
        ],
        [
          -70.642682,
          -33.392925
        ],
        [
          -70.642659,
          -33.393143
        ],
        [
          -70.642666,
          -33.394053
        ],
        [
          -70.642749,
          -33.395455
        ],
        [
          -70.642846,
          -33.397224
        ],
        [
          -70.643144,
          -33.404757
        ],
        [
          -70.645394,
          -33.423896
        ],
        [
          -70.647513,
          -33.430877
        ],
        [
          -70.648607,
          -33.432672
        ],
        [
          -70.648816,
          -33.433227
        ],
        [
          -70.650522,
          -33.432836
        ],
        [
          -70.651661,
          -33.432633
        ],
        [
          -70.652932,
          -33.432813
        ],
        [
          -70.654138,
          -33.432698
        ],
        [
          -70.655896,
          -33.432304
        ],
        [
          -70.65869,
          -33.431595
        ],
        [
          -70.661421,
          -33.430733
        ],
        [
          -70.661938,
          -33.430883
        ],
        [
          -70.662079,
          -33.431204
        ],
        [
          -70.661993,
          -33.43141
        ],
        [
          -70.66173,
          -33.431598
        ],
        [
          -70.661344,
          -33.431864
        ],
        [
          -70.661203,
          -33.432223
        ],
        [
          -70.661061,
          -33.432702
        ],
        [
          -70.66077,
          -33.434591
        ],
        [
          -70.661068,
          -33.444143
        ],
        [
          -70.658269,
          -33.454794
        ],
        [
          -70.657092,
          -33.457293
        ],
        [
          -70.657291,
          -33.461094
        ],
        [
          -70.656573,
          -33.471089
        ],
        [
          -70.654931,
          -33.474125
        ],
        [
          -70.655419,
          -33.476619
        ],
        [
          -70.656702,
          -33.479781
        ],
        [
          -70.667058,
          -33.501332
        ],
        [
          -70.681706,
          -33.531537
        ],
        [
          -70.695357,
          -33.524573
        ],
        [
          -70.696689,
          -33.523795
        ],
        [
          -70.697362,
          -33.523264
        ],
        [
          -70.697488,
          -33.523002
        ],
        [
          -70.697746,
          -33.522766
        ],
        [
          -70.697859,
          -33.522673
        ],
        [
          -70.698379,
          -33.523477
        ],
        [
          -70.698975,
          -33.524301
        ],
        [
          -70.699042,
          -33.524353
        ],
        [
          -70.699267,
          -33.524234
        ],
        [
          -70.699579,
          -33.523929
        ],
        [
          -70.701288,
          -33.524551
        ],
        [
          -70.703634,
          -33.525431
        ]
      ]
    }
  },
  {
    "metadata": {
      "id": "arc_007",
      "terminal_inicio": "MARCOLETA",
      "terminal_fin": "CONCHA Y TORO",
      "servicio": "PA-CYT-SA-AM",
      "sentido": "IDA",
      "calles": "Cabezal Marcoleta;AV. SANTA ROSA;AV. LIBERTADOR BERNARDO O´HIGGINS;CARMEN;AV. MANUEL ANTONIO MATTA;AV. VICUÑA MACKENNA;AV. VICUÑA MACKENNA;AV. VICUÑA MACKENNA;AV. CONCHA Y TORO;ARTURO PRAT;Terminal Concha y Toro",
      "notas": "",
      "activo": "sí"
    },
    "geometria": {
      "type": "LineString",
      "coordinates": [
        [
          -70.645887,
          -33.444079
        ],
        [
          -70.646241,
          -33.44291
        ],
        [
          -70.644232,
          -33.442373
        ],
        [
          -70.643544,
          -33.442584
        ],
        [
          -70.643278,
          -33.443078
        ],
        [
          -70.643206,
          -33.443408
        ],
        [
          -70.642516,
          -33.446464
        ],
        [
          -70.641963,
          -33.448755
        ],
        [
          -70.641176,
          -33.451215
        ],
        [
          -70.640534,
          -33.453824
        ],
        [
          -70.639814,
          -33.45648
        ],
        [
          -70.639522,
          -33.457635
        ],
        [
          -70.636923,
          -33.4571
        ],
        [
          -70.63573,
          -33.456846
        ],
        [
          -70.633851,
          -33.456424
        ],
        [
          -70.631229,
          -33.455881
        ],
        [
          -70.629871,
          -33.45559
        ],
        [
          -70.629036,
          -33.458685
        ],
        [
          -70.628242,
          -33.461421
        ],
        [
          -70.627004,
          -33.465721
        ],
        [
          -70.626293,
          -33.468295
        ],
        [
          -70.625192,
          -33.469496
        ],
        [
          -70.62426,
          -33.470378
        ],
        [
          -70.623676,
          -33.472829
        ],
        [
          -70.623091,
          -33.474924
        ],
        [
          -70.621959,
          -33.479338
        ],
        [
          -70.621221,
          -33.482137
        ],
        [
          -70.62023,
          -33.485623
        ],
        [
          -70.619331,
          -33.486696
        ],
        [
          -70.618779,
          -33.487282
        ],
        [
          -70.618514,
          -33.487858
        ],
        [
          -70.61823,
          -33.488947
        ],
        [
          -70.617861,
          -33.49084
        ],
        [
          -70.617133,
          -33.493844
        ],
        [
          -70.616533,
          -33.496668
        ],
        [
          -70.615441,
          -33.501818
        ],
        [
          -70.614584,
          -33.505847
        ],
        [
          -70.613937,
          -33.508014
        ],
        [
          -70.612672,
          -33.509192
        ],
        [
          -70.611149,
          -33.510747
        ],
        [
          -70.608952,
          -33.51315
        ],
        [
          -70.605498,
          -33.516864
        ],
        [
          -70.60272,
          -33.519643
        ],
        [
          -70.599228,
          -33.522519
        ],
        [
          -70.598545,
          -33.52298
        ],
        [
          -70.598148,
          -33.523511
        ],
        [
          -70.596897,
          -33.526547
        ],
        [
          -70.595597,
          -33.529763
        ],
        [
          -70.593836,
          -33.533948
        ],
        [
          -70.591171,
          -33.539622
        ],
        [
          -70.589186,
          -33.544045
        ],
        [
          -70.587828,
          -33.547216
        ],
        [
          -70.587367,
          -33.549616
        ],
        [
          -70.586731,
          -33.553579
        ],
        [
          -70.585935,
          -33.557811
        ],
        [
          -70.585299,
          -33.561723
        ],
        [
          -70.584544,
          -33.566042
        ],
        [
          -70.583414,
          -33.571859
        ],
        [
          -70.582578,
          -33.576194
        ],
        [
          -70.581741,
          -33.580655
        ],
        [
          -70.58038,
          -33.587337
        ],
        [
          -70.579328,
          -33.592684
        ],
        [
          -70.578696,
          -33.596198
        ],
        [
          -70.577822,
          -33.600012
        ],
        [
          -70.57694,
          -33.604643
        ],
        [
          -70.576074,
          -33.609011
        ],
        [
          -70.575098,
          -33.613756
        ],
        [
          -70.574426,
          -33.61371
        ],
        [
          -70.573686,
          -33.613527
        ],
        [
          -70.573384,
          -33.613721
        ]
      ]
    }
  },
  {
    "metadata": {
      "id": "arc_008",
      "terminal_inicio": "SAN JOSÉ",
      "terminal_fin": "SANTA ANA",
      "servicio": "SJ-LL",
      "sentido": "",
      "calles": "JOSE BESA; AV. SAN JOSE; BARROS ARANA; COVADONGA; FREIRE; 1; AV. COLÓN NORTE; AV. AMÉRICA; AV. OCHAGAVÍA; AV. JOSÉ JOAQUIN PRIETO VIAL; AV. JOSE JOAQUIN PRIETO VIAL; AV. JOSE JOAQUIN PRIETO VIAL; AV. VIEL; AV. MANUEL RODRÍGUEZ; SANTO DOMINGO; AV. MANUEL RODRIGUEZ",
      "notas": "",
      "activo": "sí"
    },
    "geometria": {
      "type": "LineString",
      "coordinates": [
        [
          -70.693655,
          -33.597868
        ],
        [
          -70.693814,
          -33.597835
        ],
        [
          -70.69431,
          -33.598912
        ],
        [
          -70.696386,
          -33.597868
        ],
        [
          -70.69796,
          -33.597409
        ],
        [
          -70.699829,
          -33.597136
        ],
        [
          -70.699312,
          -33.595708
        ],
        [
          -70.704624,
          -33.594654
        ],
        [
          -70.702833,
          -33.589955
        ],
        [
          -70.70802,
          -33.588679
        ],
        [
          -70.705649,
          -33.583477
        ],
        [
          -70.703177,
          -33.578126
        ],
        [
          -70.699491,
          -33.569796
        ],
        [
          -70.696779,
          -33.5641
        ],
        [
          -70.697165,
          -33.563719
        ],
        [
          -70.696287,
          -33.559884
        ],
        [
          -70.695518,
          -33.555916
        ],
        [
          -70.693283,
          -33.556115
        ],
        [
          -70.692396,
          -33.554466
        ],
        [
          -70.690668,
          -33.550752
        ],
        [
          -70.689637,
          -33.548506
        ],
        [
          -70.688185,
          -33.545226
        ],
        [
          -70.686611,
          -33.541935
        ],
        [
          -70.686168,
          -33.541011
        ],
        [
          -70.686091,
          -33.540623
        ],
        [
          -70.685388,
          -33.539452
        ],
        [
          -70.684908,
          -33.538557
        ],
        [
          -70.684342,
          -33.537504
        ],
        [
          -70.684048,
          -33.53717
        ],
        [
          -70.683286,
          -33.535718
        ],
        [
          -70.682675,
          -33.534602
        ],
        [
          -70.673588,
          -33.516589
        ],
        [
          -70.672311,
          -33.51391
        ],
        [
          -70.671225,
          -33.511667
        ],
        [
          -70.670077,
          -33.509335
        ],
        [
          -70.669039,
          -33.507014
        ],
        [
          -70.667731,
          -33.504278
        ],
        [
          -70.667165,
          -33.503091
        ],
        [
          -70.665949,
          -33.500489
        ],
        [
          -70.66158,
          -33.491157
        ],
        [
          -70.660267,
          -33.488391
        ],
        [
          -70.657354,
          -33.482179
        ],
        [
          -70.656915,
          -33.481224
        ],
        [
          -70.656678,
          -33.480766
        ],
        [
          -70.656478,
          -33.480357
        ],
        [
          -70.656127,
          -33.479624
        ],
        [
          -70.655615,
          -33.478818
        ],
        [
          -70.655488,
          -33.478599
        ],
        [
          -70.655382,
          -33.478035
        ],
        [
          -70.655235,
          -33.477565
        ],
        [
          -70.655017,
          -33.477029
        ],
        [
          -70.6548,
          -33.476598
        ],
        [
          -70.654489,
          -33.475904
        ],
        [
          -70.65433,
          -33.475425
        ],
        [
          -70.65429,
          -33.474876
        ],
        [
          -70.654277,
          -33.474422
        ],
        [
          -70.654331,
          -33.474029
        ],
        [
          -70.654582,
          -33.473379
        ],
        [
          -70.655482,
          -33.472008
        ],
        [
          -70.655983,
          -33.471095
        ],
        [
          -70.656013,
          -33.469663
        ],
        [
          -70.656177,
          -33.466646
        ],
        [
          -70.65632,
          -33.463747
        ],
        [
          -70.656466,
          -33.460539
        ],
        [
          -70.656475,
          -33.459613
        ],
        [
          -70.656486,
          -33.458468
        ],
        [
          -70.65655,
          -33.457991
        ],
        [
          -70.656754,
          -33.456525
        ],
        [
          -70.656846,
          -33.45576
        ],
        [
          -70.657694,
          -33.454557
        ],
        [
          -70.658093,
          -33.453492
        ],
        [
          -70.658588,
          -33.451686
        ],
        [
          -70.659273,
          -33.449358
        ],
        [
          -70.659639,
          -33.448307
        ],
        [
          -70.660055,
          -33.447476
        ],
        [
          -70.660559,
          -33.446739
        ],
        [
          -70.660707,
          -33.445107
        ],
        [
          -70.660354,
          -33.444197
        ],
        [
          -70.660218,
          -33.443711
        ],
        [
          -70.660008,
          -33.443043
        ],
        [
          -70.659936,
          -33.442753
        ],
        [
          -70.659884,
          -33.442492
        ],
        [
          -70.659795,
          -33.442072
        ],
        [
          -70.659697,
          -33.441605
        ],
        [
          -70.659518,
          -33.441032
        ],
        [
          -70.659354,
          -33.440574
        ],
        [
          -70.659307,
          -33.440173
        ],
        [
          -70.659345,
          -33.439729
        ],
        [
          -70.659629,
          -33.43773
        ],
        [
          -70.659714,
          -33.437118
        ],
        [
          -70.660422,
          -33.437191
        ],
        [
          -70.660299,
          -33.437984
        ],
        [
          -70.66023,
          -33.438561
        ],
        [
          -70.66023,
          -33.438561
        ]
      ]
    }
  },
  {
    "metadata": {
      "id": "arc_009",
      "terminal_inicio": "PIE ANDINO",
      "terminal_fin": "CONCHA Y TORO",
      "servicio": "PA-CYT-SA-AM",
      "sentido": "IDA",
      "calles": "Terminal Pie Andino;Av. Paseo Pie Andino;Av. Doctor Eduardo Cordero;Av. Concha y Toro;Terminal Concha y Toro",
      "notas": "",
      "activo": "sí"
    },
    "geometria": {
      "type": "LineString",
      "coordinates": [
        [
          -70.553489,
          -33.604273
        ],
        [
          -70.554159,
          -33.604439
        ],
        [
          -70.554815,
          -33.603544
        ],
        [
          -70.557229,
          -33.603737
        ],
        [
          -70.559862,
          -33.603937
        ],
        [
          -70.563508,
          -33.604237
        ],
        [
          -70.56607,
          -33.604503
        ],
        [
          -70.566611,
          -33.60463
        ],
        [
          -70.569582,
          -33.605021
        ],
        [
          -70.572337,
          -33.605403
        ],
        [
          -70.574493,
          -33.605687
        ],
        [
          -70.575767,
          -33.60587
        ],
        [
          -70.576512,
          -33.605832
        ],
        [
          -70.576664,
          -33.605906
        ],
        [
          -70.576007,
          -33.609236
        ],
        [
          -70.575353,
          -33.612336
        ],
        [
          -70.57511,
          -33.613723
        ],
        [
          -70.574963,
          -33.613785
        ],
        [
          -70.57452,
          -33.613714
        ],
        [
          -70.574378,
          -33.613705
        ],
        [
          -70.57423,
          -33.613602
        ],
        [
          -70.573908,
          -33.613507
        ],
        [
          -70.573755,
          -33.613515
        ],
        [
          -70.5736,
          -33.613586
        ]
      ]
    }
  },
  {
    "metadata": {
      "id": "arc_010",
      "terminal_inicio": "PEDRO LIRA",
      "terminal_fin": "SAN ALFONSO",
      "servicio": "PL-DC-SA2-LC",
      "sentido": "IDA",
      "calles": "Pedro Lira, Gil de Castro, Avenida Central Cardenal Raúl Silva Henríquez, Avenida Américo Vespucio Caletera, Avenida Padre Alberto Hurtado, Avenida General Velásquez Caletera, Buzeta, Ramón Subercaseaux.",
      "notas": "",
      "activo": "sí"
    },
    "geometria": {
      "type": "LineString",
      "coordinates": [
        [
          -70.702672,
          -33.525037
        ],
        [
          -70.699594,
          -33.523931
        ],
        [
          -70.699021,
          -33.524405
        ],
        [
          -70.697801,
          -33.522692
        ],
        [
          -70.698594,
          -33.522235
        ],
        [
          -70.699566,
          -33.521647
        ],
        [
          -70.700442,
          -33.521127
        ],
        [
          -70.701746,
          -33.520309
        ],
        [
          -70.702009,
          -33.520095
        ],
        [
          -70.702142,
          -33.51962
        ],
        [
          -70.702305,
          -33.518969
        ],
        [
          -70.702415,
          -33.518277
        ],
        [
          -70.702113,
          -33.517508
        ],
        [
          -70.701798,
          -33.516868
        ],
        [
          -70.701481,
          -33.516174
        ],
        [
          -70.701126,
          -33.515496
        ],
        [
          -70.700622,
          -33.514466
        ],
        [
          -70.698671,
          -33.5105
        ],
        [
          -70.697307,
          -33.507728
        ],
        [
          -70.695796,
          -33.504681
        ],
        [
          -70.695224,
          -33.503506
        ],
        [
          -70.694353,
          -33.501737
        ],
        [
          -70.693127,
          -33.499267
        ],
        [
          -70.69213,
          -33.497309
        ],
        [
          -70.688543,
          -33.488959
        ],
        [
          -70.687089,
          -33.48508
        ],
        [
          -70.685831,
          -33.481847
        ],
        [
          -70.684698,
          -33.479028
        ],
        [
          -70.684523,
          -33.478518
        ],
        [
          -70.68441,
          -33.478396
        ],
        [
          -70.68369,
          -33.478368
        ],
        [
          -70.682644,
          -33.478434
        ],
        [
          -70.681125,
          -33.478466
        ],
        [
          -70.681163,
          -33.478396
        ],
        [
          -70.681347,
          -33.478378
        ],
        [
          -70.682008,
          -33.478344
        ],
        [
          -70.683448,
          -33.47825
        ],
        [
          -70.683845,
          -33.478168
        ],
        [
          -70.684151,
          -33.47785
        ],
        [
          -70.684301,
          -33.477515
        ],
        [
          -70.68423,
          -33.477271
        ],
        [
          -70.683944,
          -33.476364
        ],
        [
          -70.683421,
          -33.475208
        ],
        [
          -70.683094,
          -33.474807
        ],
        [
          -70.68246,
          -33.473916
        ],
        [
          -70.681043,
          -33.47187
        ],
        [
          -70.680809,
          -33.471523
        ],
        [
          -70.680533,
          -33.471088
        ],
        [
          -70.680484,
          -33.470769
        ],
        [
          -70.680437,
          -33.470677
        ],
        [
          -70.680298,
          -33.470683
        ],
        [
          -70.68007,
          -33.470644
        ],
        [
          -70.679754,
          -33.470666
        ],
        [
          -70.678765,
          -33.470677
        ],
        [
          -70.678365,
          -33.47067
        ],
        [
          -70.676944,
          -33.470657
        ],
        [
          -70.675511,
          -33.470642
        ],
        [
          -70.674983,
          -33.470635
        ],
        [
          -70.67399,
          -33.470624
        ],
        [
          -70.673889,
          -33.470636
        ],
        [
          -70.673822,
          -33.470737
        ],
        [
          -70.67373,
          -33.470845
        ],
        [
          -70.672554,
          -33.470216
        ]
      ]
    }
  },
  {
    "metadata": {
      "id": "arc_011",
      "terminal_inicio": "RECOLETA",
      "terminal_fin": "SANTA ROSA",
      "servicio": "RE-LB-SR",
      "sentido": "",
      "calles": "Avenida Recoleta;Avenida Salvador Allende;Avenida Recoleta;San Antonio;San Francisco;Avenida Santa Rosa",
      "notas": "",
      "activo": "sí"
    },
    "geometria": {
      "type": "LineString",
      "coordinates": [
        [
          -70.636864,
          -33.379354
        ],
        [
          -70.636798,
          -33.379022
        ],
        [
          -70.638584,
          -33.378525
        ],
        [
          -70.640427,
          -33.382413
        ],
        [
          -70.640769,
          -33.382943
        ],
        [
          -70.640916,
          -33.383882
        ],
        [
          -70.641356,
          -33.385147
        ],
        [
          -70.642089,
          -33.387228
        ],
        [
          -70.642333,
          -33.388167
        ],
        [
          -70.642474,
          -33.390769
        ],
        [
          -70.64285,
          -33.397754
        ],
        [
          -70.643225,
          -33.405365
        ],
        [
          -70.643683,
          -33.416233
        ],
        [
          -70.644205,
          -33.420107
        ],
        [
          -70.645512,
          -33.424307
        ],
        [
          -70.648061,
          -33.431779
        ],
        [
          -70.649184,
          -33.433859
        ],
        [
          -70.648445,
          -33.438322
        ],
        [
          -70.647719,
          -33.442958
        ],
        [
          -70.647675,
          -33.443145
        ],
        [
          -70.647587,
          -33.443206
        ],
        [
          -70.647201,
          -33.443133
        ],
        [
          -70.647147,
          -33.443448
        ],
        [
          -70.647147,
          -33.444727
        ],
        [
          -70.647082,
          -33.445605
        ],
        [
          -70.647132,
          -33.448603
        ],
        [
          -70.646927,
          -33.450974
        ],
        [
          -70.646609,
          -33.453212
        ],
        [
          -70.646303,
          -33.455226
        ],
        [
          -70.645407,
          -33.45853
        ],
        [
          -70.645117,
          -33.460708
        ],
        [
          -70.644717,
          -33.462889
        ],
        [
          -70.644502,
          -33.464789
        ],
        [
          -70.644048,
          -33.468877
        ],
        [
          -70.643833,
          -33.47306
        ],
        [
          -70.643669,
          -33.476617
        ],
        [
          -70.643026,
          -33.476812
        ],
        [
          -70.642617,
          -33.477056
        ],
        [
          -70.642442,
          -33.477494
        ],
        [
          -70.642091,
          -33.47847
        ],
        [
          -70.641506,
          -33.483004
        ],
        [
          -70.639414,
          -33.501864
        ],
        [
          -70.637746,
          -33.511532
        ],
        [
          -70.637044,
          -33.514115
        ],
        [
          -70.636024,
          -33.525893
        ],
        [
          -70.634913,
          -33.532198
        ],
        [
          -70.634329,
          -33.537266
        ],
        [
          -70.634387,
          -33.540384
        ],
        [
          -70.634405,
          -33.542709
        ],
        [
          -70.63231,
          -33.553606
        ],
        [
          -70.63087,
          -33.559722
        ],
        [
          -70.630439,
          -33.56372
        ],
        [
          -70.630097,
          -33.572012
        ],
        [
          -70.629184,
          -33.581704
        ],
        [
          -70.628269,
          -33.588982
        ],
        [
          -70.627801,
          -33.595176
        ],
        [
          -70.627273,
          -33.601058
        ],
        [
          -70.627273,
          -33.608255
        ],
        [
          -70.628973,
          -33.608019
        ],
        [
          -70.628973,
          -33.608019
        ]
      ]
    }
  },
  {
    "metadata": {
      "id": "arc_012",
      "terminal_inicio": "SANTA ROSA",
      "terminal_fin": "RECOLETA",
      "servicio": "RE-LB-SR",
      "sentido": "",
      "calles": "Patio Santa Rosa;Avenida Santa Rosa;Enrique Mac Iver;Avenida Recoleta",
      "notas": "",
      "activo": "sí"
    },
    "geometria": {
      "type": "LineString",
      "coordinates": [
        [
          -70.629959,
          -33.6046
        ],
        [
          -70.626714,
          -33.604315
        ],
        [
          -70.629638,
          -33.575606
        ],
        [
          -70.630663,
          -33.561375
        ],
        [
          -70.631346,
          -33.556251
        ],
        [
          -70.632371,
          -33.551696
        ],
        [
          -70.633978,
          -33.543159
        ],
        [
          -70.634909,
          -33.531498
        ],
        [
          -70.636751,
          -33.516573
        ],
        [
          -70.638571,
          -33.507329
        ],
        [
          -70.641949,
          -33.477643
        ],
        [
          -70.642225,
          -33.469737
        ],
        [
          -70.644487,
          -33.44988
        ],
        [
          -70.645816,
          -33.444168
        ],
        [
          -70.646184,
          -33.443028
        ],
        [
          -70.646346,
          -33.442167
        ],
        [
          -70.646593,
          -33.440746
        ],
        [
          -70.647297,
          -33.436013
        ],
        [
          -70.647568,
          -33.434658
        ],
        [
          -70.647794,
          -33.434055
        ],
        [
          -70.648064,
          -33.433453
        ],
        [
          -70.647433,
          -33.430818
        ],
        [
          -70.644883,
          -33.421947
        ],
        [
          -70.643648,
          -33.417321
        ],
        [
          -70.643468,
          -33.412201
        ],
        [
          -70.642541,
          -33.397349
        ],
        [
          -70.642331,
          -33.387927
        ],
        [
          -70.640828,
          -33.383995
        ],
        [
          -70.640227,
          -33.383493
        ],
        [
          -70.640026,
          -33.383158
        ],
        [
          -70.640126,
          -33.38274
        ],
        [
          -70.640227,
          -33.38228
        ],
        [
          -70.638651,
          -33.378858
        ],
        [
          -70.637348,
          -33.378858
        ],
        [
          -70.637549,
          -33.379359
        ],
        [
          -70.637599,
          -33.379359
        ],
        [
          -70.637599,
          -33.379401
        ]
      ]
    }
  },
  {
    "metadata": {
      "id": "arc_098",
      "terminal_inicio": "NUEVA TOBALABA",
      "terminal_fin": "LO BLANCO",
      "servicio": "RE-LB-SR",
      "sentido": "IDA",
      "calles": "Av Vitacura, Av Providencia, Av Cardenal Caro, Av San Antonio, Av San Francisco, Av Santa Rosa, Avenida Lo Blanco",
      "notas": "",
      "activo": "sí"
    },
    "geometria": {
      "type": "LineString",
      "coordinates": [
        [
          -70.605106,
          -33.417409
        ],
        [
          -70.605999,
          -33.419726
        ],
        [
          -70.609177,
          -33.42287
        ],
        [
          -70.614912,
          -33.425813
        ],
        [
          -70.617587,
          -33.428096
        ],
        [
          -70.620509,
          -33.429838
        ],
        [
          -70.622179,
          -33.430037
        ],
        [
          -70.624684,
          -33.431879
        ],
        [
          -70.627315,
          -33.434415
        ],
        [
          -70.633677,
          -33.437142
        ],
        [
          -70.635355,
          -33.437128
        ],
        [
          -70.635497,
          -33.436393
        ],
        [
          -70.638991,
          -33.435629
        ],
        [
          -70.642795,
          -33.434681
        ],
        [
          -70.648782,
          -33.433246
        ],
        [
          -70.648991,
          -33.433965
        ],
        [
          -70.648365,
          -33.438014
        ],
        [
          -70.64799,
          -33.440783
        ],
        [
          -70.647656,
          -33.443141
        ],
        [
          -70.647124,
          -33.443167
        ],
        [
          -70.647015,
          -33.446673
        ],
        [
          -70.646889,
          -33.450949
        ],
        [
          -70.646198,
          -33.455305
        ],
        [
          -70.645063,
          -33.461711
        ],
        [
          -70.643596,
          -33.476622
        ],
        [
          -70.642164,
          -33.477519
        ],
        [
          -70.641923,
          -33.480813
        ],
        [
          -70.638316,
          -33.507245
        ],
        [
          -70.635259,
          -33.528828
        ],
        [
          -70.633977,
          -33.542195
        ],
        [
          -70.63124,
          -33.556779
        ],
        [
          -70.630356,
          -33.560039
        ],
        [
          -70.630415,
          -33.565734
        ],
        [
          -70.629884,
          -33.572558
        ],
        [
          -70.627999,
          -33.588608
        ],
        [
          -70.655397,
          -33.586266
        ]
      ]
    }
  },
  {
    "metadata": {
      "id": "arc_099",
      "terminal_inicio": "LO BLANCO",
      "terminal_fin": "NUEVA TOBALABA",
      "servicio": "RE-LB-SR",
      "sentido": "VUELTA",
      "calles": "Lo Blanco, Santa Rosa, Alameda, Av providencia, ",
      "notas": "",
      "activo": "sí"
    },
    "geometria": {
      "type": "LineString",
      "coordinates": [
        [
          -70.605106,
          -33.417409
        ],
        [
          -70.605999,
          -33.419726
        ],
        [
          -70.609177,
          -33.42287
        ],
        [
          -70.614912,
          -33.425813
        ],
        [
          -70.617587,
          -33.428096
        ],
        [
          -70.620509,
          -33.429838
        ],
        [
          -70.622179,
          -33.430037
        ],
        [
          -70.624684,
          -33.431879
        ],
        [
          -70.627315,
          -33.434415
        ],
        [
          -70.633677,
          -33.437142
        ],
        [
          -70.635355,
          -33.437128
        ],
        [
          -70.641367,
          -33.440915
        ],
        [
          -70.645275,
          -33.442645
        ],
        [
          -70.646327,
          -33.442824
        ],
        [
          -70.644441,
          -33.450935
        ],
        [
          -70.643283,
          -33.458374
        ],
        [
          -70.642116,
          -33.471414
        ],
        [
          -70.641939,
          -33.480801
        ],
        [
          -70.638316,
          -33.507245
        ],
        [
          -70.635259,
          -33.528828
        ],
        [
          -70.633977,
          -33.542195
        ],
        [
          -70.63124,
          -33.556779
        ],
        [
          -70.630356,
          -33.560039
        ],
        [
          -70.630415,
          -33.565734
        ],
        [
          -70.629884,
          -33.572558
        ],
        [
          -70.627999,
          -33.588608
        ],
        [
          -70.655397,
          -33.586266
        ]
      ]
    }
  },
  {
    "metadata": {
      "id": "arc_100",
      "terminal_inicio": "CARDENAL CARO",
      "terminal_fin": "LO BLANCO",
      "servicio": "RE-LB-SR",
      "sentido": "IDA",
      "calles": "Av Cardena José María Caro, San Antonio, San Francisco, Av Santa Rosa Av Lo Blanco",
      "notas": "",
      "activo": "sí"
    },
    "geometria": {
      "type": "LineString",
      "coordinates": [
        [
          -70.656508,
          -33.586173
        ],
        [
          -70.62879,
          -33.588286
        ],
        [
          -70.630239,
          -33.565495
        ],
        [
          -70.631145,
          -33.558701
        ],
        [
          -70.632413,
          -33.551606
        ],
        [
          -70.63495,
          -33.541791
        ],
        [
          -70.635596,
          -33.527593
        ],
        [
          -70.63738,
          -33.512844
        ],
        [
          -70.638272,
          -33.507142
        ],
        [
          -70.639838,
          -33.494674
        ],
        [
          -70.642035,
          -33.478368
        ],
        [
          -70.643532,
          -33.476293
        ],
        [
          -70.643814,
          -33.473391
        ],
        [
          -70.644007,
          -33.468835
        ],
        [
          -70.645409,
          -33.458567
        ],
        [
          -70.646831,
          -33.451964
        ],
        [
          -70.647182,
          -33.443262
        ],
        [
          -70.647668,
          -33.442985
        ],
        [
          -70.648826,
          -33.433158
        ],
        [
          -70.648058,
          -33.433474
        ]
      ]
    }
  },
  {
    "metadata": {
      "id": "arc_101",
      "terminal_inicio": "LO BLANCO",
      "terminal_fin": "CARDENAL CARO",
      "servicio": "RE-LB-SR",
      "sentido": "VUELTA",
      "calles": "Lo Blanco, Santa Rosa, Mac Iver",
      "notas": "",
      "activo": "sí"
    },
    "geometria": {
      "type": "LineString",
      "coordinates": [
        [
          -70.656508,
          -33.586173
        ],
        [
          -70.62879,
          -33.588286
        ],
        [
          -70.630239,
          -33.565495
        ],
        [
          -70.631145,
          -33.558701
        ],
        [
          -70.632413,
          -33.551606
        ],
        [
          -70.63495,
          -33.541791
        ],
        [
          -70.635596,
          -33.527593
        ],
        [
          -70.63738,
          -33.512844
        ],
        [
          -70.638272,
          -33.507142
        ],
        [
          -70.639838,
          -33.494674
        ],
        [
          -70.642035,
          -33.478368
        ],
        [
          -70.642026,
          -33.476169
        ],
        [
          -70.642214,
          -33.468585
        ],
        [
          -70.643357,
          -33.458114
        ],
        [
          -70.644326,
          -33.451216
        ],
        [
          -70.646013,
          -33.443201
        ],
        [
          -70.646435,
          -33.441715
        ],
        [
          -70.647535,
          -33.434824
        ],
        [
          -70.648058,
          -33.433474
        ]
      ]
    }
  },
  {
    "metadata": {
      "id": "arc_102",
      "terminal_inicio": "SANTA ROSA",
      "terminal_fin": "LORD COCHRANE",
      "servicio": "RE-LB-SR",
      "sentido": "IDA",
      "calles": "Santa Rosa, Av. Carlos Silva Vilodosola, San Diego, Av Diez de Julio Huamachuco, Lord Cochrane",
      "notas": "",
      "activo": "sí"
    },
    "geometria": {
      "type": "LineString",
      "coordinates": [
        [
          -70.627432,
          -33.596467
        ],
        [
          -70.628307,
          -33.586557
        ],
        [
          -70.628981,
          -33.580854
        ],
        [
          -70.630485,
          -33.55978
        ],
        [
          -70.633944,
          -33.542757
        ],
        [
          -70.633972,
          -33.542244
        ],
        [
          -70.634218,
          -33.541241
        ],
        [
          -70.634956,
          -33.530659
        ],
        [
          -70.635558,
          -33.528105
        ],
        [
          -70.636543,
          -33.5183
        ],
        [
          -70.63709,
          -33.513077
        ],
        [
          -70.63843,
          -33.507335
        ],
        [
          -70.639639,
          -33.495372
        ],
        [
          -70.641582,
          -33.480952
        ],
        [
          -70.641855,
          -33.477677
        ],
        [
          -70.648225,
          -33.47756
        ],
        [
          -70.648744,
          -33.463884
        ],
        [
          -70.650051,
          -33.454138
        ],
        [
          -70.654,
          -33.454518
        ],
        [
          -70.654578,
          -33.450352
        ],
        [
          -70.654967,
          -33.447925
        ],
        [
          -70.655171,
          -33.446833
        ]
      ]
    }
  },
  {
    "metadata": {
      "id": "arc_103",
      "terminal_inicio": "LORD COCHRANE",
      "terminal_fin": "SANTA ROSA",
      "servicio": "RE-LB-SR",
      "sentido": "VUELTA",
      "calles": "Vidaurre, San Ignacio de Loyola, Euclides, Orán, Carlos Valdovinos, Av Santa Rosa",
      "notas": "",
      "activo": "sí"
    },
    "geometria": {
      "type": "LineString",
      "coordinates": [
        [
          -70.654994,
          -33.447923
        ],
        [
          -70.656948,
          -33.448161
        ],
        [
          -70.656448,
          -33.450562
        ],
        [
          -70.655716,
          -33.453811
        ],
        [
          -70.655859,
          -33.455587
        ],
        [
          -70.655505,
          -33.458933
        ],
        [
          -70.655055,
          -33.46511
        ],
        [
          -70.654737,
          -33.470475
        ],
        [
          -70.653897,
          -33.477304
        ],
        [
          -70.653068,
          -33.47803
        ],
        [
          -70.650392,
          -33.478473
        ],
        [
          -70.649139,
          -33.479483
        ],
        [
          -70.641881,
          -33.480857
        ],
        [
          -70.641128,
          -33.486625
        ],
        [
          -70.63947,
          -33.499707
        ],
        [
          -70.638667,
          -33.507599
        ],
        [
          -70.63743,
          -33.513086
        ],
        [
          -70.636734,
          -33.518675
        ],
        [
          -70.635251,
          -33.530352
        ],
        [
          -70.634214,
          -33.541195
        ],
        [
          -70.634285,
          -33.542536
        ],
        [
          -70.634041,
          -33.543758
        ],
        [
          -70.630697,
          -33.55981
        ],
        [
          -70.629597,
          -33.577031
        ],
        [
          -70.62872,
          -33.585671
        ],
        [
          -70.627604,
          -33.596492
        ]
      ]
    }
  },
  {
    "metadata": {
      "id": "arc_013",
      "terminal_inicio": "SANTA ROSA",
      "terminal_fin": "ÑUBLE",
      "servicio": "RE-LB-SR",
      "sentido": "",
      "calles": "PATIO SANTA ROSA; CORREDOR SANTA ROSA; CORREDOR SANTA ROSA; AV. SANTA ROSA; CORREDOR SANTA ROSA; AV. SANTA ROSA; AV. SANTA ROSA; ÑUBLE; AV. VICUÑA MACKENNA",
      "notas": "",
      "activo": "sí"
    },
    "geometria": {
      "type": "LineString",
      "coordinates": [
        [
          -70.630421,
          -33.60607
        ],
        [
          -70.627229,
          -33.606156
        ],
        [
          -70.627267,
          -33.601987
        ],
        [
          -70.62709,
          -33.601445
        ],
        [
          -70.627668,
          -33.594996
        ],
        [
          -70.628883,
          -33.580446
        ],
        [
          -70.63003,
          -33.568147
        ],
        [
          -70.630421,
          -33.561313
        ],
        [
          -70.630331,
          -33.559663
        ],
        [
          -70.631186,
          -33.556361
        ],
        [
          -70.633397,
          -33.546112
        ],
        [
          -70.633487,
          -33.545376
        ],
        [
          -70.633699,
          -33.544252
        ],
        [
          -70.633915,
          -33.543024
        ],
        [
          -70.633955,
          -33.542386
        ],
        [
          -70.634045,
          -33.541813
        ],
        [
          -70.634148,
          -33.541344
        ],
        [
          -70.6342,
          -33.540982
        ],
        [
          -70.634256,
          -33.540262
        ],
        [
          -70.636952,
          -33.516372
        ],
        [
          -70.639283,
          -33.50074
        ],
        [
          -70.641703,
          -33.481569
        ],
        [
          -70.641725,
          -33.477928
        ],
        [
          -70.641858,
          -33.476965
        ],
        [
          -70.641991,
          -33.476321
        ],
        [
          -70.642013,
          -33.474176
        ],
        [
          -70.642025,
          -33.472989
        ],
        [
          -70.642073,
          -33.471625
        ],
        [
          -70.642157,
          -33.470382
        ],
        [
          -70.642259,
          -33.469128
        ],
        [
          -70.628328,
          -33.467596
        ],
        [
          -70.626574,
          -33.467442
        ],
        [
          -70.626455,
          -33.467849
        ]
      ]
    }
  },
  {
    "metadata": {
      "id": "arc_014",
      "terminal_inicio": "ÑUBLE",
      "terminal_fin": "SANTA ROSA",
      "servicio": "RE-LB-SR",
      "sentido": "",
      "calles": "AV. VICUÑA MACKENNA; AV. VICUÑA MACKENNA; AV. ISABEL RIQUELME; AV. SANTA ROSA; AV. SANTA ROSA; AV. SANTA ROSA; PATIO SANTA ROSA",
      "notas": "",
      "activo": "sí"
    },
    "geometria": {
      "type": "LineString",
      "coordinates": [
        [
          -70.62652,
          -33.467562
        ],
        [
          -70.62628,
          -33.46864
        ],
        [
          -70.62592,
          -33.46914
        ],
        [
          -70.625214,
          -33.469516
        ],
        [
          -70.624914,
          -33.469854
        ],
        [
          -70.624509,
          -33.470167
        ],
        [
          -70.62421,
          -33.4712
        ],
        [
          -70.621928,
          -33.479934
        ],
        [
          -70.62061,
          -33.4847
        ],
        [
          -70.620337,
          -33.485326
        ],
        [
          -70.620419,
          -33.485354
        ],
        [
          -70.621923,
          -33.485067
        ],
        [
          -70.624003,
          -33.484543
        ],
        [
          -70.625713,
          -33.484166
        ],
        [
          -70.626097,
          -33.484094
        ],
        [
          -70.626284,
          -33.483958
        ],
        [
          -70.626748,
          -33.483482
        ],
        [
          -70.627649,
          -33.482611
        ],
        [
          -70.628082,
          -33.482185
        ],
        [
          -70.628634,
          -33.481868
        ],
        [
          -70.629097,
          -33.481747
        ],
        [
          -70.629803,
          -33.481473
        ],
        [
          -70.630265,
          -33.481198
        ],
        [
          -70.631136,
          -33.480544
        ],
        [
          -70.63211,
          -33.479905
        ],
        [
          -70.632682,
          -33.479702
        ],
        [
          -70.63312,
          -33.47959
        ],
        [
          -70.633533,
          -33.479397
        ],
        [
          -70.633999,
          -33.479138
        ],
        [
          -70.634462,
          -33.478945
        ],
        [
          -70.635241,
          -33.478874
        ],
        [
          -70.635886,
          -33.478823
        ],
        [
          -70.636604,
          -33.478793
        ],
        [
          -70.637431,
          -33.478681
        ],
        [
          -70.638234,
          -33.47857
        ],
        [
          -70.638928,
          -33.478407
        ],
        [
          -70.639709,
          -33.478085
        ],
        [
          -70.640366,
          -33.477831
        ],
        [
          -70.641741,
          -33.477598
        ],
        [
          -70.642191,
          -33.477638
        ],
        [
          -70.641997,
          -33.479181
        ],
        [
          -70.64191,
          -33.481118
        ],
        [
          -70.641679,
          -33.482742
        ],
        [
          -70.641385,
          -33.48464
        ],
        [
          -70.641143,
          -33.486574
        ],
        [
          -70.640941,
          -33.488313
        ],
        [
          -70.640649,
          -33.490424
        ],
        [
          -70.640381,
          -33.492075
        ],
        [
          -70.640057,
          -33.494835
        ],
        [
          -70.639511,
          -33.499373
        ],
        [
          -70.639311,
          -33.501515
        ],
        [
          -70.639135,
          -33.503118
        ],
        [
          -70.638801,
          -33.506802
        ],
        [
          -70.638826,
          -33.50722
        ],
        [
          -70.638675,
          -33.507972
        ],
        [
          -70.638159,
          -33.509878
        ],
        [
          -70.637654,
          -33.512447
        ],
        [
          -70.637325,
          -33.513767
        ],
        [
          -70.637222,
          -33.514865
        ],
        [
          -70.636872,
          -33.516871
        ],
        [
          -70.636696,
          -33.519121
        ],
        [
          -70.636347,
          -33.522018
        ],
        [
          -70.636059,
          -33.524385
        ],
        [
          -70.635833,
          -33.526614
        ],
        [
          -70.635196,
          -33.530599
        ],
        [
          -70.634689,
          -33.534511
        ],
        [
          -70.634486,
          -33.53707
        ],
        [
          -70.634308,
          -33.540369
        ],
        [
          -70.634334,
          -33.541511
        ],
        [
          -70.634308,
          -33.542315
        ],
        [
          -70.634131,
          -33.543266
        ],
        [
          -70.634182,
          -33.543668
        ],
        [
          -70.633979,
          -33.544366
        ],
        [
          -70.633979,
          -33.544979
        ],
        [
          -70.63337,
          -33.548153
        ],
        [
          -70.631771,
          -33.55549
        ],
        [
          -70.630878,
          -33.559865
        ],
        [
          -70.630725,
          -33.561091
        ],
        [
          -70.630624,
          -33.562
        ],
        [
          -70.630396,
          -33.566339
        ],
        [
          -70.630049,
          -33.572219
        ],
        [
          -70.629561,
          -33.577634
        ],
        [
          -70.629203,
          -33.581498
        ],
        [
          -70.628815,
          -33.584638
        ],
        [
          -70.628548,
          -33.587119
        ],
        [
          -70.628183,
          -33.590164
        ],
        [
          -70.628092,
          -33.592504
        ],
        [
          -70.627726,
          -33.596007
        ],
        [
          -70.627885,
          -33.599293
        ],
        [
          -70.628966,
          -33.599175
        ],
        [
          -70.628966,
          -33.59925
        ]
      ]
    }
  },
  {
    "metadata": {
      "id": "arc_015",
      "terminal_inicio": "SANTA ROSA",
      "terminal_fin": "LO OVALLE",
      "servicio": "RE-LB-SR",
      "sentido": "",
      "calles": "PATIO SANTA ROSA; AV. SANTA ROSA; AV. SANTA ROSA; AV. ELIAS FERNÁNDEZ ALBANO; AV. ELIAS FERNÁNDEZ ALBANO; PAULINA; SERGIO CEPPI; EIM LO OVALLE",
      "notas": "",
      "activo": "sí"
    },
    "geometria": {
      "type": "LineString",
      "coordinates": [
        [
          -70.628888,
          -33.605271
        ],
        [
          -70.627062,
          -33.605271
        ],
        [
          -70.626945,
          -33.6021
        ],
        [
          -70.627528,
          -33.595006
        ],
        [
          -70.628211,
          -33.586961
        ],
        [
          -70.628755,
          -33.58188
        ],
        [
          -70.629338,
          -33.575342
        ],
        [
          -70.62969,
          -33.572389
        ],
        [
          -70.629885,
          -33.567857
        ],
        [
          -70.630001,
          -33.566141
        ],
        [
          -70.630267,
          -33.561372
        ],
        [
          -70.630655,
          -33.558846
        ],
        [
          -70.631238,
          -33.556709
        ],
        [
          -70.631821,
          -33.553601
        ],
        [
          -70.632555,
          -33.550141
        ],
        [
          -70.632943,
          -33.547324
        ],
        [
          -70.633487,
          -33.545154
        ],
        [
          -70.633876,
          -33.543147
        ],
        [
          -70.633929,
          -33.54279
        ],
        [
          -70.633964,
          -33.542134
        ],
        [
          -70.634066,
          -33.54179
        ],
        [
          -70.634168,
          -33.541402
        ],
        [
          -70.634168,
          -33.541203
        ],
        [
          -70.634232,
          -33.540764
        ],
        [
          -70.634281,
          -33.540242
        ],
        [
          -70.63431,
          -33.539381
        ],
        [
          -70.634352,
          -33.538713
        ],
        [
          -70.634402,
          -33.537866
        ],
        [
          -70.634456,
          -33.536903
        ],
        [
          -70.634541,
          -33.534579
        ],
        [
          -70.635402,
          -33.528071
        ],
        [
          -70.63558,
          -33.528004
        ],
        [
          -70.63613,
          -33.528104
        ],
        [
          -70.63669,
          -33.528087
        ],
        [
          -70.638169,
          -33.527913
        ],
        [
          -70.645476,
          -33.526923
        ],
        [
          -70.646292,
          -33.526397
        ],
        [
          -70.647015,
          -33.526042
        ],
        [
          -70.660335,
          -33.52346
        ],
        [
          -70.662397,
          -33.523126
        ],
        [
          -70.661917,
          -33.521753
        ],
        [
          -70.661665,
          -33.520876
        ],
        [
          -70.661345,
          -33.519579
        ],
        [
          -70.660887,
          -33.518188
        ],
        [
          -70.661383,
          -33.517391
        ],
        [
          -70.663276,
          -33.516757
        ],
        [
          -70.662364,
          -33.513411
        ],
        [
          -70.658338,
          -33.514668
        ],
        [
          -70.658372,
          -33.515108
        ],
        [
          -70.658395,
          -33.515099
        ]
      ]
    }
  },
  {
    "metadata": {
      "id": "arc_016",
      "terminal_inicio": "LO OVALLE",
      "terminal_fin": "SANTA ROSA",
      "servicio": "RE-LB-SR",
      "sentido": "",
      "calles": "EIM LO OVALLE; SERGIO CARVAJAL; PAULINA; GRAN AVENIDA JOSÉ MIGUEL CARRERA; AV. ELIAS FERNÁNDEZ ALBANO; AV. ELIAS FERNÁNDEZ ALBANO; AV. SANTA ROSA; AV. SANTA ROSA; PATIO SANTA ROSA",
      "notas": "",
      "activo": "sí"
    },
    "geometria": {
      "type": "LineString",
      "coordinates": [
        [
          -70.658415,
          -33.514635
        ],
        [
          -70.662427,
          -33.51342
        ],
        [
          -70.663054,
          -33.515606
        ],
        [
          -70.659062,
          -33.51694
        ],
        [
          -70.658935,
          -33.516993
        ],
        [
          -70.660644,
          -33.523554
        ],
        [
          -70.65311,
          -33.525081
        ],
        [
          -70.647314,
          -33.526229
        ],
        [
          -70.646583,
          -33.526453
        ],
        [
          -70.646256,
          -33.526582
        ],
        [
          -70.645968,
          -33.526774
        ],
        [
          -70.645698,
          -33.526934
        ],
        [
          -70.639844,
          -33.527786
        ],
        [
          -70.637344,
          -33.528203
        ],
        [
          -70.636382,
          -33.528315
        ],
        [
          -70.635651,
          -33.528347
        ],
        [
          -70.635575,
          -33.529148
        ],
        [
          -70.634872,
          -33.533428
        ],
        [
          -70.634525,
          -33.53726
        ],
        [
          -70.634381,
          -33.540906
        ],
        [
          -70.634369,
          -33.541602
        ],
        [
          -70.634369,
          -33.542192
        ],
        [
          -70.634286,
          -33.542956
        ],
        [
          -70.634117,
          -33.544135
        ],
        [
          -70.633912,
          -33.54522
        ],
        [
          -70.633592,
          -33.546567
        ],
        [
          -70.633313,
          -33.548146
        ],
        [
          -70.632861,
          -33.550632
        ],
        [
          -70.632292,
          -33.552989
        ],
        [
          -70.631825,
          -33.555132
        ],
        [
          -70.631293,
          -33.557743
        ],
        [
          -70.630853,
          -33.559792
        ],
        [
          -70.630728,
          -33.56066
        ],
        [
          -70.630695,
          -33.561861
        ],
        [
          -70.630662,
          -33.563704
        ],
        [
          -70.630593,
          -33.565821
        ],
        [
          -70.63042,
          -33.567696
        ],
        [
          -70.62996,
          -33.573573
        ],
        [
          -70.629195,
          -33.581503
        ],
        [
          -70.628624,
          -33.586657
        ],
        [
          -70.628627,
          -33.587757
        ],
        [
          -70.627865,
          -33.59461
        ],
        [
          -70.627296,
          -33.603749
        ],
        [
          -70.627139,
          -33.605535
        ],
        [
          -70.628446,
          -33.605318
        ],
        [
          -70.628446,
          -33.605361
        ]
      ]
    }
  },
  {
    "metadata": {
      "id": "arc_017",
      "terminal_inicio": "SANTA ANA",
      "terminal_fin": "SAN JOSE",
      "servicio": "SJ-LL",
      "sentido": "REGRESO",
      "calles": "V. MANUEL RODRIGUEZ; AV. VIEL; AV. JOSE JOAQUIN PRIETO VIAL; AV. JOSE JOAQUIN PRIETO VIAL; AV. JOSE JOAQUIN PRIETO VIAL; ENLACE ORIENTE AV. AMÉRICO VESPUCIO; AV. AMERICO VESPUCIO; GRAN AVENIDA JOSÉ MIGUEL CARRERA; GRAN AVENIDA JOSÉ MIGUEL CARRERA; GRAN AVENIDA JOSÉ MIGUEL CARRERA; BALMACEDA; URMENETA; SAN JOSÉ; JOSÉ BESA",
      "notas": "",
      "activo": "SI"
    },
    "geometria": null
  },
  {
    "metadata": {
      "id": "arc_018",
      "terminal_inicio": "LOS LIBERTADORES",
      "terminal_fin": "SANTA ANA",
      "servicio": "LL-SJ",
      "sentido": "IDA",
      "calles": "LOS LIBERTADORES; AV. AMERICO VESPUCIO; AV. INDEPENDENCIA; AV. FERMIN VIVACETA; AV. FERMIN VIVACETA; AV. MANUEL RODRIGUEZ NORTE; AV. MANUEL RODRIGUEZ",
      "notas": "",
      "activo": "SI"
    },
    "geometria": null
  },
  {
    "metadata": {
      "id": "arc_019",
      "terminal_inicio": "MAPOCHO- AV BRASIL",
      "terminal_fin": "DUCAUD",
      "servicio": "PL-DC-SA2-LC",
      "sentido": "IDA",
      "calles": "Avenida Mapocho; Avenida Manuel Rodríguez Norte; Avenida Manuel Rodríguez; Avenida Manuel Rodríguez Sur; Avenida Viel; Avenida Centenario; San Ignacio de Loyola; Euclides; Orán; Avenida Alcalde Carlos Valdovinos; Gran Avenida José Miguel Carrera; Avenida Padre Hurtado; San Jose; Avenida Ducaud",
      "notas": "",
      "activo": "si"
    },
    "geometria": {
      "type": "LineString",
      "coordinates": [
        [
          -70.665181,
          -33.430866
        ],
        [
          -70.66509,
          -33.432048
        ],
        [
          -70.66302,
          -33.432079
        ],
        [
          -70.661615,
          -33.432084
        ],
        [
          -70.661335,
          -33.43207
        ],
        [
          -70.66129,
          -33.4321
        ],
        [
          -70.661215,
          -33.432155
        ],
        [
          -70.661073,
          -33.432732
        ],
        [
          -70.660913,
          -33.43359
        ],
        [
          -70.660491,
          -33.43631
        ],
        [
          -70.660208,
          -33.438625
        ],
        [
          -70.660132,
          -33.439683
        ],
        [
          -70.660124,
          -33.439943
        ],
        [
          -70.660216,
          -33.440595
        ],
        [
          -70.660358,
          -33.441439
        ],
        [
          -70.66073,
          -33.442906
        ],
        [
          -70.660865,
          -33.443549
        ],
        [
          -70.660999,
          -33.44407
        ],
        [
          -70.661033,
          -33.444546
        ],
        [
          -70.660903,
          -33.444924
        ],
        [
          -70.660842,
          -33.445548
        ],
        [
          -70.660661,
          -33.446792
        ],
        [
          -70.660443,
          -33.447812
        ],
        [
          -70.660175,
          -33.448608
        ],
        [
          -70.659723,
          -33.450178
        ],
        [
          -70.65923,
          -33.451827
        ],
        [
          -70.659012,
          -33.452613
        ],
        [
          -70.658766,
          -33.453623
        ],
        [
          -70.658656,
          -33.453995
        ],
        [
          -70.658498,
          -33.454513
        ],
        [
          -70.658343,
          -33.45478
        ],
        [
          -70.658199,
          -33.455
        ],
        [
          -70.658045,
          -33.455573
        ],
        [
          -70.65788,
          -33.4562
        ],
        [
          -70.657791,
          -33.456423
        ],
        [
          -70.657745,
          -33.456498
        ],
        [
          -70.657639,
          -33.456533
        ],
        [
          -70.657229,
          -33.456517
        ],
        [
          -70.657124,
          -33.456485
        ],
        [
          -70.657061,
          -33.45652
        ],
        [
          -70.656924,
          -33.457051
        ],
        [
          -70.656856,
          -33.457524
        ],
        [
          -70.656872,
          -33.457921
        ],
        [
          -70.65695,
          -33.458325
        ],
        [
          -70.657075,
          -33.459112
        ],
        [
          -70.657184,
          -33.45994
        ],
        [
          -70.657145,
          -33.460676
        ],
        [
          -70.657089,
          -33.461517
        ],
        [
          -70.656957,
          -33.463652
        ],
        [
          -70.656898,
          -33.464697
        ],
        [
          -70.656842,
          -33.465594
        ],
        [
          -70.656819,
          -33.466203
        ],
        [
          -70.656784,
          -33.467141
        ],
        [
          -70.656694,
          -33.468642
        ],
        [
          -70.656698,
          -33.469213
        ],
        [
          -70.656667,
          -33.469854
        ],
        [
          -70.656612,
          -33.47042
        ],
        [
          -70.656581,
          -33.471
        ],
        [
          -70.656557,
          -33.471306
        ],
        [
          -70.656495,
          -33.471573
        ],
        [
          -70.656366,
          -33.471697
        ],
        [
          -70.656284,
          -33.471879
        ],
        [
          -70.656124,
          -33.472124
        ],
        [
          -70.655647,
          -33.472798
        ],
        [
          -70.655542,
          -33.472993
        ],
        [
          -70.65519,
          -33.47344
        ],
        [
          -70.655046,
          -33.4737
        ],
        [
          -70.654975,
          -33.473977
        ],
        [
          -70.654804,
          -33.47474
        ],
        [
          -70.654812,
          -33.474922
        ],
        [
          -70.654828,
          -33.47529
        ],
        [
          -70.654858,
          -33.475508
        ],
        [
          -70.654827,
          -33.475593
        ],
        [
          -70.654258,
          -33.475744
        ],
        [
          -70.654118,
          -33.475794
        ],
        [
          -70.654035,
          -33.476559
        ],
        [
          -70.653948,
          -33.477274
        ],
        [
          -70.653934,
          -33.477316
        ],
        [
          -70.653731,
          -33.477343
        ],
        [
          -70.653435,
          -33.477555
        ],
        [
          -70.652761,
          -33.478055
        ],
        [
          -70.652398,
          -33.478167
        ],
        [
          -70.651811,
          -33.47826
        ],
        [
          -70.651177,
          -33.478359
        ],
        [
          -70.650536,
          -33.478413
        ],
        [
          -70.65017,
          -33.478585
        ],
        [
          -70.649372,
          -33.479372
        ],
        [
          -70.649063,
          -33.479549
        ],
        [
          -70.648718,
          -33.479554
        ],
        [
          -70.64839,
          -33.479612
        ],
        [
          -70.648417,
          -33.479917
        ],
        [
          -70.648781,
          -33.480967
        ],
        [
          -70.649349,
          -33.482984
        ],
        [
          -70.649757,
          -33.484389
        ],
        [
          -70.650206,
          -33.486016
        ],
        [
          -70.65043,
          -33.486987
        ],
        [
          -70.650751,
          -33.488045
        ],
        [
          -70.651154,
          -33.489566
        ],
        [
          -70.651445,
          -33.490602
        ],
        [
          -70.651719,
          -33.491654
        ],
        [
          -70.651945,
          -33.492642
        ],
        [
          -70.652165,
          -33.493504
        ],
        [
          -70.652341,
          -33.49414
        ],
        [
          -70.652615,
          -33.495109
        ],
        [
          -70.652966,
          -33.496429
        ],
        [
          -70.653139,
          -33.496951
        ],
        [
          -70.653317,
          -33.49773
        ],
        [
          -70.65369,
          -33.498943
        ],
        [
          -70.65392,
          -33.499728
        ],
        [
          -70.654261,
          -33.500876
        ],
        [
          -70.654486,
          -33.501658
        ],
        [
          -70.654656,
          -33.502325
        ],
        [
          -70.654941,
          -33.503098
        ],
        [
          -70.65532,
          -33.504495
        ],
        [
          -70.655694,
          -33.505908
        ],
        [
          -70.656086,
          -33.507141
        ],
        [
          -70.656596,
          -33.509266
        ],
        [
          -70.657063,
          -33.510702
        ],
        [
          -70.657513,
          -33.512249
        ],
        [
          -70.657782,
          -33.5133
        ],
        [
          -70.658123,
          -33.514495
        ],
        [
          -70.658303,
          -33.515036
        ],
        [
          -70.658568,
          -33.51621
        ],
        [
          -70.659007,
          -33.517525
        ],
        [
          -70.659152,
          -33.518306
        ],
        [
          -70.660187,
          -33.521818
        ],
        [
          -70.66134,
          -33.525727
        ],
        [
          -70.661658,
          -33.527053
        ],
        [
          -70.662224,
          -33.529153
        ],
        [
          -70.662762,
          -33.531029
        ],
        [
          -70.663339,
          -33.533237
        ],
        [
          -70.663607,
          -33.534323
        ],
        [
          -70.664095,
          -33.536102
        ],
        [
          -70.664484,
          -33.536922
        ],
        [
          -70.664693,
          -33.537532
        ],
        [
          -70.664789,
          -33.538038
        ],
        [
          -70.664747,
          -33.53886
        ],
        [
          -70.665213,
          -33.540592
        ],
        [
          -70.665446,
          -33.541409
        ],
        [
          -70.66572,
          -33.542274
        ],
        [
          -70.665797,
          -33.542519
        ],
        [
          -70.665816,
          -33.54297
        ],
        [
          -70.666014,
          -33.543804
        ],
        [
          -70.666706,
          -33.546161
        ],
        [
          -70.667155,
          -33.547997
        ],
        [
          -70.66779,
          -33.550535
        ],
        [
          -70.667971,
          -33.550941
        ],
        [
          -70.668121,
          -33.551521
        ],
        [
          -70.66837,
          -33.552525
        ],
        [
          -70.66853,
          -33.553086
        ],
        [
          -70.668673,
          -33.553584
        ],
        [
          -70.669019,
          -33.55486
        ],
        [
          -70.669153,
          -33.555225
        ],
        [
          -70.669289,
          -33.555855
        ],
        [
          -70.669473,
          -33.556378
        ],
        [
          -70.669713,
          -33.557224
        ],
        [
          -70.669867,
          -33.557812
        ],
        [
          -70.670064,
          -33.558493
        ],
        [
          -70.670251,
          -33.559062
        ],
        [
          -70.670407,
          -33.559665
        ],
        [
          -70.670537,
          -33.560125
        ],
        [
          -70.670857,
          -33.561198
        ],
        [
          -70.671228,
          -33.562455
        ],
        [
          -70.671279,
          -33.562793
        ],
        [
          -70.671375,
          -33.563103
        ],
        [
          -70.671475,
          -33.563609
        ],
        [
          -70.680248,
          -33.595637
        ],
        [
          -70.680466,
          -33.596511
        ],
        [
          -70.680612,
          -33.597237
        ],
        [
          -70.680747,
          -33.597739
        ],
        [
          -70.680988,
          -33.598612
        ],
        [
          -70.681116,
          -33.599101
        ],
        [
          -70.681293,
          -33.599823
        ],
        [
          -70.681513,
          -33.600686
        ],
        [
          -70.681655,
          -33.601235
        ],
        [
          -70.68184,
          -33.601907
        ],
        [
          -70.681987,
          -33.602555
        ],
        [
          -70.682371,
          -33.603937
        ],
        [
          -70.682478,
          -33.604435
        ],
        [
          -70.682613,
          -33.604866
        ],
        [
          -70.682717,
          -33.604808
        ],
        [
          -70.683054,
          -33.604642
        ],
        [
          -70.683917,
          -33.604196
        ],
        [
          -70.684648,
          -33.603812
        ],
        [
          -70.685618,
          -33.603288
        ],
        [
          -70.685951,
          -33.60311
        ],
        [
          -70.685709,
          -33.602774
        ],
        [
          -70.685342,
          -33.602297
        ],
        [
          -70.685059,
          -33.601995
        ],
        [
          -70.684987,
          -33.602014
        ],
        [
          -70.684787,
          -33.602003
        ],
        [
          -70.684789,
          -33.602008
        ]
      ]
    }
  },
  {
    "metadata": {
      "id": "arc_020",
      "terminal_inicio": "DUCAUD",
      "terminal_fin": "MAPOCHO- AV BRASIL",
      "servicio": "PL-DC-SA2-LC",
      "sentido": "REGRESO",
      "calles": "Avenida Ducaud; Condell; Avenida Padre Hurtado; Ernesto Riquelme; Gran Avenida José Miguel Carrera; San Diego; Tarapacá; Zenteno; Morandé; Avenida Presidente Balmaceda; Avenida Brasil.",
      "notas": "",
      "activo": "si"
    },
    "geometria": {
      "type": "LineString",
      "coordinates": [
        [
          -70.684731,
          -33.601146
        ],
        [
          -70.684811,
          -33.601139
        ],
        [
          -70.684471,
          -33.59984
        ],
        [
          -70.68404,
          -33.598237
        ],
        [
          -70.68379,
          -33.598279
        ],
        [
          -70.682769,
          -33.598627
        ],
        [
          -70.68199,
          -33.598841
        ],
        [
          -70.681152,
          -33.599098
        ],
        [
          -70.681075,
          -33.599103
        ],
        [
          -70.681001,
          -33.598992
        ],
        [
          -70.680926,
          -33.598746
        ],
        [
          -70.680457,
          -33.596877
        ],
        [
          -70.680119,
          -33.595543
        ],
        [
          -70.679846,
          -33.594503
        ],
        [
          -70.679584,
          -33.593499
        ],
        [
          -70.679291,
          -33.592408
        ],
        [
          -70.678892,
          -33.590934
        ],
        [
          -70.678538,
          -33.589643
        ],
        [
          -70.678262,
          -33.588393
        ],
        [
          -70.677892,
          -33.587008
        ],
        [
          -70.67745,
          -33.585433
        ],
        [
          -70.677003,
          -33.583825
        ],
        [
          -70.676597,
          -33.582341
        ],
        [
          -70.676077,
          -33.580558
        ],
        [
          -70.675689,
          -33.579192
        ],
        [
          -70.675043,
          -33.576969
        ],
        [
          -70.674586,
          -33.575304
        ],
        [
          -70.674201,
          -33.573803
        ],
        [
          -70.673522,
          -33.571357
        ],
        [
          -70.672846,
          -33.568942
        ],
        [
          -70.672488,
          -33.567693
        ],
        [
          -70.672168,
          -33.566412
        ],
        [
          -70.671755,
          -33.564963
        ],
        [
          -70.67144,
          -33.563751
        ],
        [
          -70.671049,
          -33.562358
        ],
        [
          -70.670734,
          -33.561077
        ],
        [
          -70.670422,
          -33.56016
        ],
        [
          -70.670078,
          -33.558947
        ],
        [
          -70.669718,
          -33.557624
        ],
        [
          -70.669313,
          -33.556292
        ],
        [
          -70.668943,
          -33.554929
        ],
        [
          -70.668555,
          -33.553578
        ],
        [
          -70.668209,
          -33.552454
        ],
        [
          -70.66801,
          -33.551652
        ],
        [
          -70.667832,
          -33.550946
        ],
        [
          -70.667845,
          -33.550754
        ],
        [
          -70.667615,
          -33.549838
        ],
        [
          -70.667348,
          -33.548752
        ],
        [
          -70.667068,
          -33.547641
        ],
        [
          -70.666808,
          -33.546605
        ],
        [
          -70.666769,
          -33.546341
        ],
        [
          -70.667276,
          -33.546072
        ],
        [
          -70.668145,
          -33.545614
        ],
        [
          -70.66818,
          -33.545589
        ],
        [
          -70.66737,
          -33.544554
        ],
        [
          -70.666041,
          -33.542915
        ],
        [
          -70.665511,
          -33.542134
        ],
        [
          -70.665333,
          -33.541697
        ],
        [
          -70.665043,
          -33.540584
        ],
        [
          -70.664776,
          -33.539568
        ],
        [
          -70.664511,
          -33.538572
        ],
        [
          -70.664447,
          -33.538285
        ],
        [
          -70.66426,
          -33.537529
        ],
        [
          -70.664171,
          -33.53715
        ],
        [
          -70.663977,
          -33.53633
        ],
        [
          -70.663797,
          -33.535517
        ],
        [
          -70.663588,
          -33.534686
        ],
        [
          -70.663378,
          -33.533868
        ],
        [
          -70.663301,
          -33.533693
        ],
        [
          -70.663184,
          -33.533268
        ],
        [
          -70.663018,
          -33.532604
        ],
        [
          -70.662757,
          -33.531667
        ],
        [
          -70.662644,
          -33.53125
        ],
        [
          -70.662431,
          -33.530443
        ],
        [
          -70.662221,
          -33.52952
        ],
        [
          -70.662156,
          -33.529323
        ],
        [
          -70.66192,
          -33.528582
        ],
        [
          -70.661859,
          -33.528318
        ],
        [
          -70.661647,
          -33.527581
        ],
        [
          -70.66135,
          -33.526515
        ],
        [
          -70.661087,
          -33.525469
        ],
        [
          -70.661039,
          -33.525239
        ],
        [
          -70.660753,
          -33.524308
        ],
        [
          -70.660681,
          -33.524044
        ],
        [
          -70.660482,
          -33.523356
        ],
        [
          -70.660385,
          -33.523012
        ],
        [
          -70.660242,
          -33.522495
        ],
        [
          -70.659875,
          -33.521325
        ],
        [
          -70.659706,
          -33.520587
        ],
        [
          -70.659352,
          -33.519315
        ],
        [
          -70.658948,
          -33.518003
        ],
        [
          -70.658631,
          -33.516913
        ],
        [
          -70.658506,
          -33.51637
        ],
        [
          -70.658315,
          -33.515679
        ],
        [
          -70.658142,
          -33.515095
        ],
        [
          -70.657978,
          -33.514518
        ],
        [
          -70.657796,
          -33.513855
        ],
        [
          -70.657539,
          -33.512935
        ],
        [
          -70.65745,
          -33.512614
        ],
        [
          -70.657203,
          -33.511754
        ],
        [
          -70.657094,
          -33.511383
        ],
        [
          -70.656812,
          -33.510461
        ],
        [
          -70.656671,
          -33.509894
        ],
        [
          -70.656499,
          -33.509307
        ],
        [
          -70.65625,
          -33.508531
        ],
        [
          -70.656128,
          -33.508033
        ],
        [
          -70.656148,
          -33.507972
        ],
        [
          -70.65585,
          -33.506965
        ],
        [
          -70.654835,
          -33.503476
        ],
        [
          -70.653504,
          -33.498789
        ],
        [
          -70.651773,
          -33.492491
        ],
        [
          -70.650207,
          -33.486574
        ],
        [
          -70.648767,
          -33.481297
        ],
        [
          -70.648299,
          -33.479767
        ],
        [
          -70.648196,
          -33.479587
        ],
        [
          -70.648161,
          -33.478
        ],
        [
          -70.648206,
          -33.47666
        ],
        [
          -70.648342,
          -33.473527
        ],
        [
          -70.648474,
          -33.470947
        ],
        [
          -70.648531,
          -33.469775
        ],
        [
          -70.648662,
          -33.467453
        ],
        [
          -70.648758,
          -33.466129
        ],
        [
          -70.648855,
          -33.46382
        ],
        [
          -70.648947,
          -33.462455
        ],
        [
          -70.649029,
          -33.461004
        ],
        [
          -70.64909,
          -33.459721
        ],
        [
          -70.649424,
          -33.457778
        ],
        [
          -70.649815,
          -33.455494
        ],
        [
          -70.650023,
          -33.454103
        ],
        [
          -70.650512,
          -33.451039
        ],
        [
          -70.650883,
          -33.448679
        ],
        [
          -70.651084,
          -33.447454
        ],
        [
          -70.652317,
          -33.447591
        ],
        [
          -70.652816,
          -33.445005
        ],
        [
          -70.65301,
          -33.443873
        ],
        [
          -70.653308,
          -33.442262
        ],
        [
          -70.653841,
          -33.438751
        ],
        [
          -70.654308,
          -33.435392
        ],
        [
          -70.654433,
          -33.434338
        ],
        [
          -70.654721,
          -33.432573
        ],
        [
          -70.657239,
          -33.431978
        ],
        [
          -70.658922,
          -33.431496
        ],
        [
          -70.660981,
          -33.430778
        ],
        [
          -70.662623,
          -33.430512
        ],
        [
          -70.663603,
          -33.43063
        ],
        [
          -70.664702,
          -33.430603
        ],
        [
          -70.665138,
          -33.430489
        ],
        [
          -70.665138,
          -33.43114
        ],
        [
          -70.665088,
          -33.431931
        ]
      ]
    }
  },
  {
    "metadata": {
      "id": "arc_021",
      "terminal_inicio": "EIM LA CISTERNA ",
      "terminal_fin": "DUCAUD",
      "servicio": "PL-DC-SA2-LC",
      "sentido": "IDA",
      "calles": "Gran Avenida José Miguel Carrera; Avenida Padre Hurtado; San Jose; Avenida Ducaud",
      "notas": "",
      "activo": "si"
    },
    "geometria": {
      "type": "LineString",
      "coordinates": [
        [
          -70.664599,
          -33.538857
        ],
        [
          -70.664893,
          -33.540122
        ],
        [
          -70.665358,
          -33.541758
        ],
        [
          -70.665689,
          -33.542532
        ],
        [
          -70.665775,
          -33.542755
        ],
        [
          -70.666163,
          -33.544228
        ],
        [
          -70.666641,
          -33.546029
        ],
        [
          -70.666842,
          -33.546785
        ],
        [
          -70.667206,
          -33.548148
        ],
        [
          -70.667605,
          -33.549747
        ],
        [
          -70.668016,
          -33.551138
        ],
        [
          -70.668424,
          -33.552756
        ],
        [
          -70.669853,
          -33.55768
        ],
        [
          -70.671244,
          -33.562567
        ],
        [
          -70.672434,
          -33.566985
        ],
        [
          -70.673285,
          -33.570069
        ],
        [
          -70.674084,
          -33.572834
        ],
        [
          -70.675173,
          -33.576889
        ],
        [
          -70.676609,
          -33.581843
        ],
        [
          -70.676768,
          -33.582544
        ],
        [
          -70.677858,
          -33.586398
        ],
        [
          -70.678318,
          -33.588217
        ],
        [
          -70.679049,
          -33.590951
        ],
        [
          -70.679794,
          -33.593993
        ],
        [
          -70.681101,
          -33.599137
        ],
        [
          -70.68263,
          -33.604839
        ],
        [
          -70.685854,
          -33.603161
        ],
        [
          -70.685234,
          -33.602262
        ],
        [
          -70.684821,
          -33.601183
        ],
        [
          -70.684787,
          -33.601181
        ]
      ]
    }
  },
  {
    "metadata": {
      "id": "arc_022",
      "terminal_inicio": "DUCAUD",
      "terminal_fin": "EIM LA CISTERNA ",
      "servicio": "PL-DC-SA2-LC",
      "sentido": "REGRESO",
      "calles": "Avenida Ducaud; Condell; Avenida Padre Hurtado; Ernesto Riquelme; Gran Avenida José Miguel Carrera; Estacion Intermodal La Cisterna.",
      "notas": "",
      "activo": "si"
    },
    "geometria": {
      "type": "LineString",
      "coordinates": [
        [
          -70.684718,
          -33.601192
        ],
        [
          -70.684815,
          -33.601175
        ],
        [
          -70.684268,
          -33.599021
        ],
        [
          -70.684064,
          -33.598239
        ],
        [
          -70.683776,
          -33.598331
        ],
        [
          -70.682514,
          -33.598708
        ],
        [
          -70.681105,
          -33.599088
        ],
        [
          -70.680991,
          -33.598621
        ],
        [
          -70.680569,
          -33.597022
        ],
        [
          -70.680273,
          -33.595863
        ],
        [
          -70.679984,
          -33.594663
        ],
        [
          -70.679793,
          -33.593733
        ],
        [
          -70.679432,
          -33.592392
        ],
        [
          -70.679124,
          -33.591249
        ],
        [
          -70.679042,
          -33.590981
        ],
        [
          -70.678621,
          -33.589412
        ],
        [
          -70.678352,
          -33.588385
        ],
        [
          -70.67797,
          -33.587028
        ],
        [
          -70.677628,
          -33.585587
        ],
        [
          -70.67726,
          -33.584406
        ],
        [
          -70.676783,
          -33.582568
        ],
        [
          -70.676595,
          -33.581818
        ],
        [
          -70.675826,
          -33.579246
        ],
        [
          -70.675071,
          -33.576673
        ],
        [
          -70.67442,
          -33.574261
        ],
        [
          -70.673733,
          -33.571694
        ],
        [
          -70.67313,
          -33.569625
        ],
        [
          -70.672423,
          -33.566821
        ],
        [
          -70.671744,
          -33.564447
        ],
        [
          -70.671114,
          -33.562145
        ],
        [
          -70.670477,
          -33.559975
        ],
        [
          -70.669857,
          -33.557698
        ],
        [
          -70.66936,
          -33.556039
        ],
        [
          -70.668763,
          -33.553904
        ],
        [
          -70.668147,
          -33.551601
        ],
        [
          -70.66674,
          -33.546357
        ],
        [
          -70.6683,
          -33.545535
        ],
        [
          -70.66731,
          -33.544283
        ],
        [
          -70.665724,
          -33.542221
        ],
        [
          -70.665158,
          -33.54028
        ],
        [
          -70.664782,
          -33.538884
        ],
        [
          -70.664757,
          -33.538391
        ],
        [
          -70.664738,
          -33.537863
        ],
        [
          -70.664656,
          -33.53754
        ],
        [
          -70.664301,
          -33.537638
        ]
      ]
    }
  }
]